ape_keyring/__init__.py
ape_keyring/_secrets.py
ape_keyring/accounts.py
ape_keyring/args.py
ape_keyring/config.py
ape_keyring/exceptions.py
ape_keyring/py.typed
ape_keyring/storage.py
ape_keyring/testing.py
ape_keyring/utils.py
ape_keyring/version.py
ape_keyring/_cli/__init__.py
ape_keyring/_cli/accounts.py
ape_keyring/_cli/secrets.py
ape_keyring-0.8.0.dist-info/LICENSE
ape_keyring-0.8.0.dist-info/METADATA
ape_keyring-0.8.0.dist-info/WHEEL
ape_keyring-0.8.0.dist-info/entry_points.txt
ape_keyring-0.8.0.dist-info/top_level.txt
ape_keyring-0.8.0.dist-info/RECORD
